<?xml version="1.0" encoding="utf-8" ?>
<dwsync>
<file name="13277ff20cb730cae77cbf934622993c.jpg" server="111.171.219.246" local="130778745898674944" remote="130759697400000000" Dst="0" />
<file name="22251fbdfe160e4e21b5cf68d95ea21c.jpg" server="111.171.219.246" local="130778745901175087" remote="130759697400000000" Dst="0" />
<file name="264e693bba51273db4d94527b1686b35.jpg" server="111.171.219.246" local="130778745901245091" remote="130759697400000000" Dst="0" />
<file name="28e0ff13b8dee031f696a932cb5da085.jpg" server="111.171.219.246" local="130778745901875127" remote="130759697400000000" Dst="0" />
<file name="434a47221852bc00f1460a130bafccdf.jpg" server="111.171.219.246" local="130778745902975190" remote="130759697400000000" Dst="0" />
<file name="358be8c2125952167e968c7861b7ea01.jpg" server="111.171.219.246" local="130778745908385499" remote="130759697400000000" Dst="0" />
<file name="443c5ec6c157fe65230e1ce7a6074844.jpg" server="111.171.219.246" local="130778745908445502" remote="130759697400000000" Dst="0" />
<file name="305ad87e80133bf50c99ec6255afd101.jpg" server="111.171.219.246" local="130778745908665515" remote="130759697400000000" Dst="0" />
<file name="52a3d584ab2f6f3fb27dfbc2657ab0b1.jpg" server="111.171.219.246" local="130778745908705517" remote="130759697400000000" Dst="0" />
<file name="3748cd8f49c30297cae3b8affb94637a.jpg" server="111.171.219.246" local="130778745908775521" remote="130759697400000000" Dst="0" />
<file name="59ac13c9449eb2052630c51798915ad4.jpg" server="111.171.219.246" local="130778745908835525" remote="130759697400000000" Dst="0" />
<file name="623d16a789ac128d12e7bb0c39669e90.jpg" server="111.171.219.246" local="130778745909455560" remote="130759697400000000" Dst="0" />
<file name="63d7d57f93c1af454bdb85c0dd3dc080.jpg" server="111.171.219.246" local="130778745915255892" remote="130759697400000000" Dst="0" />
<file name="63003ff104b2777b6a3b73e6c83652bd.jpg" server="111.171.219.246" local="130778745915675916" remote="130759697400000000" Dst="0" />
<file name="7f1d69f236fe470fd6e117f6aa288b0a.jpg" server="111.171.219.246" local="130778745915735919" remote="130759697400000000" Dst="0" />
<file name="81f08dbae3144ac74ba7613cbb691f38.jpg" server="111.171.219.246" local="130778745915785922" remote="130761281400000000" Dst="0" />
<file name="8adcfecd454f1058bb1bf2e6f3ac1e56.jpg" server="111.171.219.246" local="130778745915815924" remote="130759697400000000" Dst="0" />
<file name="6ab2474577940c4d9e5b8b433959caa2.jpg" server="111.171.219.246" local="130778745918836097" remote="130759697400000000" Dst="0" />
<file name="8cdf324be2a43a0ce423113e1684ab59.jpg" server="111.171.219.246" local="130778745919396129" remote="130759697400000000" Dst="0" />
<file name="8ee542bc435d89cc720a4753f3606784.jpg" server="111.171.219.246" local="130778745931046795" remote="130759697400000000" Dst="0" />
<file name="9a6f330493d7dfb7c0b5096ed30affe8.jpg" server="111.171.219.246" local="130778745932286866" remote="130759697400000000" Dst="0" />
<file name="928040aaf77536e7340d04950701cdc6.jpg" server="111.171.219.246" local="130778745932326868" remote="130759697400000000" Dst="0" />
<file name="9807b0350647bb888acaf21a833b9278.jpg" server="111.171.219.246" local="130778745939787295" remote="130759697400000000" Dst="0" />
<file name="acaa7f637b8de169a17a45fe576cdbc9.jpg" server="111.171.219.246" local="130778745939897301" remote="130759697400000000" Dst="0" />
<file name="WHF15report_2_01rr.jpg" server="111.171.219.246" local="130778745939947304" remote="130759697400000000" Dst="0" />
<file name="af23e1064c9a6f2adb2fac88e5259beb.jpg" server="111.171.219.246" local="130778745940117314" remote="130759697400000000" Dst="0" />
<file name="WHF15report_2_03r.jpg" server="111.171.219.246" local="130778745940197319" remote="130759697400000000" Dst="0" />
<file name="cb8fdd8d41e63f034205e3a026fed946.jpg" server="111.171.219.246" local="130778745944587570" remote="130759697400000000" Dst="0" />
<file name="afeeceae2ae8e1651d253a58a99b839a.jpg" server="111.171.219.246" local="130778745945947647" remote="130759697400000000" Dst="0" />
<file name="b3a2d2f74f3089a3407ef25678bae348.jpg" server="111.171.219.246" local="130778745946047653" remote="130759697400000000" Dst="0" />
<file name="c364f860c82bae7e01fa1b93a8ab9fc7.jpg" server="111.171.219.246" local="130778745949247836" remote="130759697400000000" Dst="0" />
<file name="dff4e94189a56cbe3571068855e6fa84.jpg" server="111.171.219.246" local="130778745951327955" remote="130759697400000000" Dst="0" />
<file name="ea1edc253e9c105de1ed5f24afccad49.jpg" server="111.171.219.246" local="130778745951367957" remote="130759697400000000" Dst="0" />
<file name="ba549ffc92637b627e37af58e0742645.jpg" server="111.171.219.246" local="130778745951457963" remote="130759697400000000" Dst="0" />
<file name="f8627039819d8f050e429645f05da34a.jpg" server="111.171.219.246" local="130778745951527967" remote="130759697400000000" Dst="0" />
<file name="ff34f7df4f6a5770b18f0e895b0d8c5e.jpg" server="111.171.219.246" local="130778745951577969" remote="130759697400000000" Dst="0" />
<file name="fcbe83acda00905d92c066d494e5b708.jpg" server="111.171.219.246" local="130778745966398817" remote="130759697400000000" Dst="0" />
<file name="whf15win_th.jpg" server="111.171.219.246" local="130778745966508823" remote="130759697400000000" Dst="0" />
</dwsync>