<?xml version="1.0" encoding="utf-8" ?>
<dwsync>
<file name="animated-overlay.gif" server="111.171.219.246" local="130813116782208159" remote="130782481800000000" Dst="0" />
<file name="ui-bg_flat_0_aaaaaa_40x100.png" server="111.171.219.246" local="130813116785728360" remote="130782481800000000" Dst="0" />
<file name="ui-bg_flat_75_ffffff_40x100.png" server="111.171.219.246" local="130813116782238160" remote="130782481800000000" Dst="0" />
<file name="ui-bg_glass_55_fbf9ee_1x400.png" server="111.171.219.246" local="130813116783768248" remote="130782481800000000" Dst="0" />
<file name="ui-bg_glass_65_ffffff_1x400.png" server="111.171.219.246" local="130813116783088209" remote="130782481800000000" Dst="0" />
<file name="ui-bg_glass_75_dadada_1x400.png" server="111.171.219.246" local="130813116782998204" remote="130782481800000000" Dst="0" />
<file name="ui-bg_glass_75_e6e6e6_1x400.png" server="111.171.219.246" local="130813116782978203" remote="130782481800000000" Dst="0" />
<file name="ui-bg_glass_95_fef1ec_1x400.png" server="111.171.219.246" local="130813116783798250" remote="130782481800000000" Dst="0" />
<file name="ui-bg_highlight-soft_75_cccccc_1x100.png" server="111.171.219.246" local="130813116782318165" remote="130782481800000000" Dst="0" />
<file name="ui-icons_222222_256x240.png" server="111.171.219.246" local="130813116783958259" remote="130782481800000000" Dst="0" />
<file name="ui-icons_2e83ff_256x240.png" server="111.171.219.246" local="130813116785138326" remote="130782481800000000" Dst="0" />
<file name="ui-icons_454545_256x240.png" server="111.171.219.246" local="130813116784698301" remote="130782481800000000" Dst="0" />
<file name="ui-icons_888888_256x240.png" server="111.171.219.246" local="130813116784488289" remote="130782481800000000" Dst="0" />
<file name="ui-icons_cd0a0a_256x240.png" server="111.171.219.246" local="130813116785298335" remote="130782481800000000" Dst="0" />
</dwsync>